HandlingAndProcessingStringsInR/README.md
HandlingAndProcessingStringsInR/__init__.py
HandlingAndProcessingStringsInR/__main__.py
HandlingAndProcessingStringsInR/file.pdf
HandlingAndProcessingStringsInR/index.html
handling_and_processing_strings_in_r-2024.3.4.0.dist-info/METADATA
handling_and_processing_strings_in_r-2024.3.4.0.dist-info/WHEEL
handling_and_processing_strings_in_r-2024.3.4.0.dist-info/entry_points.txt
handling_and_processing_strings_in_r-2024.3.4.0.dist-info/top_level.txt
handling_and_processing_strings_in_r-2024.3.4.0.dist-info/RECORD
